README.md
setup.py
bkzep/__init__.py
bkzep/io.py
bkzep.egg-info/PKG-INFO
bkzep.egg-info/SOURCES.txt
bkzep.egg-info/dependency_links.txt
bkzep.egg-info/requires.txt
bkzep.egg-info/top_level.txt