Metadata-Version: 1.0
Name: bkzep
Version: 0.5.0
Summary: Python package for using bokeh in Apache Zeppelin Notebook
Home-page: https://github.com/zjffdu/bkzep
Author: Jeff Zhang
Author-email: zjffdu@apache.org
License: Apache Licence V2.0
Platform: UNKNOWN
